lamp_ai/__init__.py
lamp_ai/lamp_ai.py
lamp_ai-0.6.0.dist-info/LICENSE
lamp_ai-0.6.0.dist-info/METADATA
lamp_ai-0.6.0.dist-info/WHEEL
lamp_ai-0.6.0.dist-info/top_level.txt
lamp_ai-0.6.0.dist-info/RECORD
