Metadata-Version: 2.1
Name: lamp-ai
Version: 0.6.0
Summary: A library for controlling LAMP AI devices
Author: Rossi
Author-email: rizzieang@gmail.com
Classifier: Programming Language :: Python :: 3
Classifier: License :: OSI Approved :: MIT License
Classifier: Operating System :: OS Independent
Requires-Python: >=3.6
License-File: LICENSE
Requires-Dist: pyserial
Requires-Dist: numpy
